setup.py
CanIStreamIt.egg-info/PKG-INFO
CanIStreamIt.egg-info/SOURCES.txt
CanIStreamIt.egg-info/dependency_links.txt
CanIStreamIt.egg-info/requires.txt
CanIStreamIt.egg-info/top_level.txt
canistreamit/__init__.py
canistreamit/canistreamit.py