Metadata-Version: 1.1
Name: CanIStreamIt
Version: 0.1
Summary: Can I Stream It api
Home-page: https://github.com/Bulv1ne/CanIStreamIt
Author: Niels Lemmens
Author-email: draso.odin@gmail.com
License: MIT
Platform: any
Classifier: Development Status :: 4 - Beta
Classifier: Intended Audience :: Developers
Classifier: License :: OSI Approved :: MIT License
Classifier: Operating System :: OS Independent
Classifier: Programming Language :: Python
Classifier: Programming Language :: Python :: 3
Classifier: Topic :: Software Development :: Libraries :: Python Modules
